thermometer/__init__.py
thermometer/dallas_18s20/__init__.py
thermometer/dallas_18s20/w1.py
thermometer-0.1.9.dist-info/metadata.json
thermometer-0.1.9.dist-info/DESCRIPTION.rst
thermometer-0.1.9.dist-info/METADATA
thermometer-0.1.9.dist-info/RECORD
thermometer-0.1.9.dist-info/top_level.txt
thermometer-0.1.9.dist-info/WHEEL
