Metadata-Version: 2.0
Name: thermometer
Version: 0.1.9
Summary: thermometer library for IoT
Home-page: https://webeye.services/
Author: Václav Rak
Author-email: rak@webeye.services
License: MIT License
Platform: UNKNOWN
Classifier: Topic :: System :: Monitoring
Classifier: Topic :: System :: Logging
Classifier: License :: OSI Approved :: MIT License
Classifier: Operating System :: OS Independent
Classifier: Programming Language :: Python :: 2.7
